{
  "name": "roq/kucoin_pro/json/OrdersAckDataItemsItem",
  "type": "dictionary",
  "values": [
    {
      "name": "id",
      "type": "std/string_view"
    },
    {
      "name": "symbol",
      "type": "std/string_view"
    },
    {
      "name": "type",
      "type": "roq/kucoin_pro/json/OrderType"
    },
    {
      "name": "side",
      "type": "roq/kucoin_pro/json/Side"
    },
    {
      "name": "price",
      "type": "std/double"
    },
    {
      "name": "size",
      "type": "std/double"
    },
    {
      "name": "value",
      "type": "std/double"
    },
    {
      "name": "dealValue",
      "type": "std/double"
    },
    {
      "name": "dealSize",
      "type": "std/double"
    },
    {
      "name": "stp",
      "type": "roq/kucoin_pro/json/SelfTradePrevention"
    },
    {
      "name": "stop",
      "type": "roq/kucoin_pro/json/StopPriceType"
    },
    {
      "name": "stopPriceType",
      "type": "roq/kucoin_pro/json/StopPriceType"
    },
    {
      "name": "stopTriggered",
      "type": "std/bool"
    },
    {
      "name": "stopPrice",
      "type": "std/double"
    },
    {
      "name": "timeInForce",
      "type": "roq/kucoin_pro/json/TimeInForce"
    },
    {
      "name": "postOnly",
      "type": "std/bool"
    },
    {
      "name": "hidden",
      "type": "std/bool"
    },
    {
      "name": "iceberg",
      "type": "std/bool"
    },
    {
      "name": "leverage",
      "type": "std/double"
    },
    {
      "name": "forceHold",
      "type": "std/bool"
    },
    {
      "name": "closeOrder",
      "type": "std/bool"
    },
    {
      "name": "visibleSize",
      "type": "std/double"
    },
    {
      "name": "clientOid",
      "type": "std/string_view"
    },
    {
      "name": "remark",
      "type": "std/string_view"
    },
    {
      "name": "tags",
      "type": "std/string_view"
    },
    {
      "name": "isActive",
      "type": "std/bool"
    },
    {
      "name": "cancelExist",
      "type": "std/bool"
    },
    {
      "name": "createdAt",
      "type": "std/milliseconds"
    },
    {
      "name": "updatedAt",
      "type": "std/milliseconds"
    },
    {
      "name": "endAt",
      "type": "std/milliseconds"
    },
    {
      "name": "orderTime",
      "type": "std/nanoseconds"
    },
    {
      "name": "settleCurrency",
      "type": "std/string_view"
    },
    {
      "name": "marginMode",
      "type": "roq/kucoin_pro/json/MarginMode"
    },
    {
      "name": "avgDealPrice",
      "type": "std/double"
    },
    {
      "name": "status",
      "type": "roq/kucoin_pro/json/OrderStatus"
    },
    {
      "name": "filledSize",
      "type": "std/double"
    },
    {
      "name": "filledValue",
      "type": "std/double"
    },
    {
      "name": "reduceOnly",
      "type": "std/bool"
    },
    {
      "name": "positionSide",
      "type": "roq/kucoin_pro/json/PositionSide"
    }
  ]
}
