{
  "name": "roq/kucoin_pro/protocol/json/AccountAckDataAccountsItemCurrenciesItem",
  "type": "dictionary",
  "values": [
    {
      "name": "currency",
      "type": "std/string_view"
    },
    {
      "name": "equity",
      "type": "std/double"
    },
    {
      "name": "hold",
      "type": "std/double"
    },
    {
      "name": "balance",
      "type": "std/double"
    },
    {
      "name": "available",
      "type": "std/double"
    },
    {
      "name": "liability",
      "type": "std/double"
    },
    {
      "name": "potentialBorrow",
      "type": "std/double"
    },
    {
      "name": "collateralStatus",
      "type": "std/int32"
    }
  ]
}
